<?xml version="1.0" encoding="UTF-8" ?>
<!DOCTYPE mapper PUBLIC "-//mybatis.org//DTD Mapper 3.0//EN" "http://mybatis.org/dtd/mybatis-3-mapper.dtd" >
<mapper namespace="com.aotubuy.Dao.TRoleMapper" >
  <resultMap id="BaseResultMap" type="com.aotubuy.Model.TRole" >
    <!--
      WARNING - @mbggenerated
      This element is automatically generated by MyBatis Generator, do not modify.
    -->
    <id column="id" property="id" jdbcType="INTEGER" />
    <result column="name" property="name" jdbcType="VARCHAR" />
    <result column="description" property="description" jdbcType="VARCHAR" />
    <result column="dept_id" property="deptId" jdbcType="INTEGER" />
    <result column="create_time" property="createTime" jdbcType="TIMESTAMP" />
  </resultMap>
  <delete id="deleteByPrimaryKey" parameterType="java.lang.Integer" >
    <!--
      WARNING - @mbggenerated
      This element is automatically generated by MyBatis Generator, do not modify.
    -->
    delete from t_role
    where id = #{id,jdbcType=INTEGER}
  </delete>
  <insert id="insert" parameterType="com.aotubuy.Model.TRole" >
    <!--
      WARNING - @mbggenerated
      This element is automatically generated by MyBatis Generator, do not modify.
    -->
    <selectKey resultType="java.lang.Integer" keyProperty="id" order="AFTER" >
      SELECT LAST_INSERT_ID()
    </selectKey>
    insert into t_role (`name`, description, dept_id, 
      create_time)
    values (#{name,jdbcType=VARCHAR}, #{description,jdbcType=VARCHAR}, #{deptId,jdbcType=INTEGER}, 
      #{createTime,jdbcType=TIMESTAMP})
  </insert>
  <update id="updateByPrimaryKey" parameterType="com.aotubuy.Model.TRole" >
    <!--
      WARNING - @mbggenerated
      This element is automatically generated by MyBatis Generator, do not modify.
    -->
    update t_role
    set `name` = #{name,jdbcType=VARCHAR},
      description = #{description,jdbcType=VARCHAR},
      dept_id = #{deptId,jdbcType=INTEGER},
      create_time = #{createTime,jdbcType=TIMESTAMP}
    where id = #{id,jdbcType=INTEGER}
  </update>
  <select id="selectByPrimaryKey" resultMap="BaseResultMap" parameterType="java.lang.Integer" >
    <!--
      WARNING - @mbggenerated
      This element is automatically generated by MyBatis Generator, do not modify.
    -->
    select id, `name`, description, dept_id, create_time
    from t_role
    where id = #{id,jdbcType=INTEGER}
  </select>
  <select id="selectAll" resultMap="BaseResultMap" >
    <!--
      WARNING - @mbggenerated
      This element is automatically generated by MyBatis Generator, do not modify.
    -->
    select id, `name`, description, dept_id, create_time
    from t_role
  </select>
</mapper>